{
  "repo_name": "FarmWebsite",
  "repo_full_name": "futuredayssoftware/farmwebsite",
  "repo_owner": "FutureDaysSoftware",
  "repo_description": null,
  "repo_private": false,
  "repo_fork": false,
  "schemas": [
    {
      "name": "schema.graphql",
      "path": "schema.graphql",
      "sha": "ab17355381288e303e0132353b019d81d0586767",
      "url": "https://api.github.com/repositories/115011965/contents/schema.graphql?ref=3c4960259084f545ac3a496893cc474ced7d1b67",
      "git_url": "https://api.github.com/repositories/115011965/git/blobs/ab17355381288e303e0132353b019d81d0586767",
      "html_url": "https://github.com/FutureDaysSoftware/FarmWebsite/blob/3c4960259084f545ac3a496893cc474ced7d1b67/schema.graphql",
      "content": "schema {\n  query: Query\n  mutation: Mutation\n}\n\ntype Query {\n  error: Boolean\n}\n\ntype Mutation {\n  addProduct(input: ProductInput!): Product!\n}\n\ntype Product {\n  name: String!\n  id: ID!\n  createDate: Float!\n  status: String\n  quantity: Int!\n}\n\ninput ProductInput {\n  name: String!\n  quantity: Int!\n}\n",
      "containsQueryType": true,
      "validSchema": true,
      "contentDuplicate": false,
      "numObjectTypes": 3,
      "containsCycle": false,
      "polynomialLevel": 0,
      "numDefinitions": 5
    }
  ],
  "metrics": {
    "created_at": "2017-12-21T14:03:19Z",
    "updated_at": "2018-10-26T02:19:46Z",
    "pushed_at": "2018-11-23T06:10:19Z",
    "issues": 0,
    "watchers": 0,
    "fork_count": 0,
    "has_wiki_enabled": true,
    "license": "mit",
    "pull_requests": 12,
    "pull_requests_open": 2,
    "pull_requests_closed": 3,
    "pull_requests_merged": 7,
    "releases": 0,
    "stargazers": 0
  }
}